[
  {
    "id": "sc-0e4ada84e0",
    "address": "306   \n     \n              \r\n         APR",
    "zip": "43600",
    "county": "Lucas",
    "market": "lucas",
    "stage": "Auction",
    "filed": "2026-04-10",
    "auction": null,
    "est_value": null,
    "source": "Toledo Legal News",
    "url": "https://www.toledolegalnews.com/legal_notices/foreclosure_sherrif_sales_lucas/",
    "notes": "306   \n     \n              \r\n         Apr 6,",
    "tax_owed": null,
    "redemption_period": "",
    "tax_rate": null,
    "scraped": "2026-04-10"
  },
  {
    "id": "sc-e34165c053",
    "address": "026     \n         \n                         \n                              \r\n   ",
    "zip": "43600",
    "county": "Lucas",
    "market": "lucas",
    "stage": "Auction",
    "filed": "2026-04-10",
    "auction": null,
    "est_value": null,
    "source": "Toledo Legal News",
    "url": "https://www.toledolegalnews.com/legal_notices/foreclosure_sherrif_sales_lucas/",
    "notes": "026     \n         \n                         \n                              \r\n         \r\n                 \r\n                    \r\n                      \r\n                 \r\n                 Facebook \r\n",
    "tax_owed": null,
    "redemption_period": "",
    "tax_rate": null,
    "scraped": "2026-04-10"
  },
  {
    "id": "sc-45c5a27c7f",
    "address": "581   \n     \n              \r\n         APR",
    "zip": "43600",
    "county": "Lucas",
    "market": "lucas",
    "stage": "Auction",
    "filed": "2026-04-10",
    "auction": null,
    "est_value": null,
    "source": "Toledo Legal News",
    "url": "https://www.toledolegalnews.com/legal_notices/foreclosure_sherrif_sales_lucas/",
    "notes": "581   \n     \n              \r\n         Apr 6,",
    "tax_owed": null,
    "redemption_period": "",
    "tax_rate": null,
    "scraped": "2026-04-10"
  },
  {
    "id": "sc-a5e1e28c54",
    "address": "870   \n     \n              \r\n         APR",
    "zip": "43600",
    "county": "Lucas",
    "market": "lucas",
    "stage": "Auction",
    "filed": "2026-04-10",
    "auction": null,
    "est_value": null,
    "source": "Toledo Legal News",
    "url": "https://www.toledolegalnews.com/legal_notices/foreclosure_sherrif_sales_lucas/",
    "notes": "870   \n     \n              \r\n         Apr 6,",
    "tax_owed": null,
    "redemption_period": "",
    "tax_rate": null,
    "scraped": "2026-04-10"
  },
  {
    "id": "sc-867905ab67",
    "address": "611   \n     \n              \r\n         APR",
    "zip": "43600",
    "county": "Lucas",
    "market": "lucas",
    "stage": "Auction",
    "filed": "2026-04-10",
    "auction": null,
    "est_value": null,
    "source": "Toledo Legal News",
    "url": "https://www.toledolegalnews.com/legal_notices/foreclosure_sherrif_sales_lucas/",
    "notes": "611   \n     \n              \r\n         Apr 6,",
    "tax_owed": null,
    "redemption_period": "",
    "tax_rate": null,
    "scraped": "2026-04-10"
  },
  {
    "id": "sc-999b0c7807",
    "address": "473   \n     \n              \r\n         APR",
    "zip": "43600",
    "county": "Lucas",
    "market": "lucas",
    "stage": "Auction",
    "filed": "2026-04-10",
    "auction": null,
    "est_value": null,
    "source": "Toledo Legal News",
    "url": "https://www.toledolegalnews.com/legal_notices/foreclosure_sherrif_sales_lucas/",
    "notes": "473   \n     \n              \r\n         Apr 6,",
    "tax_owed": null,
    "redemption_period": "",
    "tax_rate": null,
    "scraped": "2026-04-10"
  },
  {
    "id": "sc-1b1bf56727",
    "address": "238   \n     \n              \r\n         APR",
    "zip": "43600",
    "county": "Lucas",
    "market": "lucas",
    "stage": "Auction",
    "filed": "2026-04-10",
    "auction": null,
    "est_value": null,
    "source": "Toledo Legal News",
    "url": "https://www.toledolegalnews.com/legal_notices/foreclosure_sherrif_sales_lucas/",
    "notes": "238   \n     \n              \r\n         Apr 6,",
    "tax_owed": null,
    "redemption_period": "",
    "tax_rate": null,
    "scraped": "2026-04-10"
  },
  {
    "id": "sc-ddc3a2efe4",
    "address": "026   \n     \n              \r\n         MAR",
    "zip": "43600",
    "county": "Lucas",
    "market": "lucas",
    "stage": "Auction",
    "filed": "2026-04-10",
    "auction": null,
    "est_value": null,
    "source": "Toledo Legal News",
    "url": "https://www.toledolegalnews.com/legal_notices/foreclosure_sherrif_sales_lucas/",
    "notes": "026   \n     \n              \r\n         Mar 25,",
    "tax_owed": null,
    "redemption_period": "",
    "tax_rate": null,
    "scraped": "2026-04-10"
  },
  {
    "id": "sc-f89bb9a007",
    "address": "994   \n     \n              \r\n         MAR",
    "zip": "43600",
    "county": "Lucas",
    "market": "lucas",
    "stage": "Auction",
    "filed": "2026-04-10",
    "auction": null,
    "est_value": null,
    "source": "Toledo Legal News",
    "url": "https://www.toledolegalnews.com/legal_notices/foreclosure_sherrif_sales_lucas/",
    "notes": "994   \n     \n              \r\n         Mar 23,",
    "tax_owed": null,
    "redemption_period": "",
    "tax_rate": null,
    "scraped": "2026-04-10"
  },
  {
    "id": "sc-b8419111ef",
    "address": "508   \n     \n              \r\n         MAR",
    "zip": "43600",
    "county": "Lucas",
    "market": "lucas",
    "stage": "Auction",
    "filed": "2026-04-10",
    "auction": null,
    "est_value": null,
    "source": "Toledo Legal News",
    "url": "https://www.toledolegalnews.com/legal_notices/foreclosure_sherrif_sales_lucas/",
    "notes": "508   \n     \n              \r\n         Mar 23,",
    "tax_owed": null,
    "redemption_period": "",
    "tax_rate": null,
    "scraped": "2026-04-10"
  },
  {
    "id": "sc-d04aebee10",
    "address": "122   \n     \n              \r\n         MAR",
    "zip": "43600",
    "county": "Lucas",
    "market": "lucas",
    "stage": "Auction",
    "filed": "2026-04-10",
    "auction": null,
    "est_value": null,
    "source": "Toledo Legal News",
    "url": "https://www.toledolegalnews.com/legal_notices/foreclosure_sherrif_sales_lucas/",
    "notes": "122   \n     \n              \r\n         Mar 23,",
    "tax_owed": null,
    "redemption_period": "",
    "tax_rate": null,
    "scraped": "2026-04-10"
  }
]